cabfile.py
cabinet.py
cabfile-1.0.0.dist-info/DESCRIPTION.rst
cabfile-1.0.0.dist-info/METADATA
cabfile-1.0.0.dist-info/RECORD
cabfile-1.0.0.dist-info/WHEEL
cabfile-1.0.0.dist-info/metadata.json
cabfile-1.0.0.dist-info/top_level.txt
