Metadata-Version: 2.0
Name: cabfile
Version: 1.0.0
Summary: Cabinet file reader for python
Home-page: http://bitbucket.org/krisvale/pycabinet/
Author: Kristján Valur Jónsson
Author-email: sweskman@gmail.com
License: OTHER
Keywords: archiving cabinet
Platform: UNKNOWN
Classifier: Development Status :: 5 - Production/Stable
Classifier: License :: Other/Proprietary License
Classifier: Operating System :: Microsoft :: Windows
Classifier: Topic :: System :: Archiving
Classifier: Programming Language :: Python :: 2.7
Classifier: Programming Language :: Python :: 3
